asciiscape/__init__.py
asciiscape/__main__.py
asciiscape/console.py
asciiscape/imgUtils.py
asciiscape-0.1.7.0.dist-info/METADATA
asciiscape-0.1.7.0.dist-info/WHEEL
asciiscape-0.1.7.0.dist-info/RECORD
