Metadata-Version: 2.1
Name: asciiscape
Version: 0.1.7.0
Summary: A simple CLI Python tool for converting image to ASCII textpe
Author: Lucca Chiguti
Author-email: luccachbusiness@gmail.com
Requires-Python: >=3.12,<4.0
Classifier: Programming Language :: Python :: 3
Classifier: Programming Language :: Python :: 3.12
Requires-Dist: numpy (>=1.26.4,<2.0.0)
Requires-Dist: pillow (>=10.3.0,<11.0.0)
Requires-Dist: rich (>=13.7.1,<14.0.0)
